odoo/addons/account_invoice_margin_sale_delivered_sync/README.rst
odoo/addons/account_invoice_margin_sale_delivered_sync/__init__.py
odoo/addons/account_invoice_margin_sale_delivered_sync/__manifest__.py
odoo/addons/account_invoice_margin_sale_delivered_sync/i18n/account_invoice_margin_sale_delivered_sync.pot
odoo/addons/account_invoice_margin_sale_delivered_sync/i18n/es.po
odoo/addons/account_invoice_margin_sale_delivered_sync/models/__init__.py
odoo/addons/account_invoice_margin_sale_delivered_sync/models/account_invoice.py
odoo/addons/account_invoice_margin_sale_delivered_sync/models/sale.py
odoo/addons/account_invoice_margin_sale_delivered_sync/readme/CONTRIBUTORS.rst
odoo/addons/account_invoice_margin_sale_delivered_sync/readme/DESCRIPTION.rst
odoo/addons/account_invoice_margin_sale_delivered_sync/static/description/icon.png
odoo/addons/account_invoice_margin_sale_delivered_sync/static/description/index.html
odoo/addons/account_invoice_margin_sale_delivered_sync/tests/__init__.py
odoo/addons/account_invoice_margin_sale_delivered_sync/tests/test_account_invoice_margin_sale_delivered_sync.py
odoo12_addon_account_invoice_margin_sale_delivered_sync-12.0.1.0.1.dist-info/METADATA
odoo12_addon_account_invoice_margin_sale_delivered_sync-12.0.1.0.1.dist-info/WHEEL
odoo12_addon_account_invoice_margin_sale_delivered_sync-12.0.1.0.1.dist-info/top_level.txt
odoo12_addon_account_invoice_margin_sale_delivered_sync-12.0.1.0.1.dist-info/RECORD
